nuwan_colors/__init__.py
nuwan_colors/core.py
nuwan_colors-0.1.2.dist-info/METADATA
nuwan_colors-0.1.2.dist-info/WHEEL
nuwan_colors-0.1.2.dist-info/top_level.txt
nuwan_colors-0.1.2.dist-info/RECORD
